lastfm_mpris2_scrobbler/Cache.py
lastfm_mpris2_scrobbler/PlayerState.py
lastfm_mpris2_scrobbler/Scrobbler.py
lastfm_mpris2_scrobbler/__init__.py
lastfm_mpris2_scrobbler/__main__.py
lastfm_mpris2_scrobbler/globals.py
lastfm_mpris2_scrobbler-1.0.5.dist-info/licenses/LICENSE
lastfm_mpris2_scrobbler-1.0.5.dist-info/METADATA
lastfm_mpris2_scrobbler-1.0.5.dist-info/WHEEL
lastfm_mpris2_scrobbler-1.0.5.dist-info/entry_points.txt
lastfm_mpris2_scrobbler-1.0.5.dist-info/top_level.txt
lastfm_mpris2_scrobbler-1.0.5.dist-info/RECORD
