Metadata-Version: 2.4
Name: lastfm-mpris2-scrobbler
Version: 1.0.5
Summary: Last.fm scrobbler via MPRIS2 in Linux
Home-page: https://github.com/Ladbaby/lastfm-scrobbler
Author: Ladbaby
Author-email: Ladbabyms@outlook.com
License: MIT
License-File: LICENSE
Requires-Dist: coloredlogs
Requires-Dist: mpris2
Requires-Dist: pylast
Requires-Dist: PyYAML
Requires-Dist: dbus-python
Requires-Dist: pyxdg
Dynamic: author
Dynamic: author-email
Dynamic: description
Dynamic: description-content-type
Dynamic: home-page
Dynamic: license
Dynamic: license-file
Dynamic: requires-dist
Dynamic: summary
